openapi_to_sdk/__init__.py
openapi_to_sdk/function.py
openapi_to_sdk/sdk_automation.py
openapi_to_sdk/writer.py
openapi_to_sdk-0.1.4.dist-info/LICENSE
openapi_to_sdk-0.1.4.dist-info/METADATA
openapi_to_sdk-0.1.4.dist-info/WHEEL
openapi_to_sdk-0.1.4.dist-info/top_level.txt
openapi_to_sdk-0.1.4.dist-info/RECORD
