Metadata-Version: 2.1
Name: openapi-to-sdk
Version: 0.1.4
Summary: API to Python SDK
Home-page: UNKNOWN
Author: OnSearch Pty Ltd
Author-email: dev@vctr.ai
License: Apache
Keywords: SDK to API Automation.
Platform: UNKNOWN
Requires-Python: >=3
